{"authorDailyContributionsMap":{"lihaoyangML":[{"date":"2021-01-18","commitResults":[{"hash":"c380181ff9c7396d21406a765b8aa71285075ed4","messageTitle":"Update readme to reflect new IntelliJ version","messageBody":"","fileTypesAndContributionMap":{"md":{"insertions":10,"deletions":10}}},{"hash":"8cf74a9bf270a216eeedae558b9ebe1681ed3386","messageTitle":"Update README.md","messageBody":"","fileTypesAndContributionMap":{"md":{"insertions":2,"deletions":2}}}]},{"date":"2021-01-19","commitResults":[{"hash":"d1affd08c2656ad24720bc310f744bd69d302081","messageTitle":"add greets and exits for Duke","messageBody":"","fileTypesAndContributionMap":{"java":{"insertions":6,"deletions":6}}}]},{"date":"2021-01-27","commitResults":[{"hash":"125c39ef8d44b079c153d375b33f49d4d2377000","messageTitle":"Add Echo, update Greet and Exit","messageBody":"","tags":["Level-1"],"fileTypesAndContributionMap":{"java":{"insertions":12,"deletions":6}}},{"hash":"86db7ccb0fdf0c63b0f06c3b098a9e843dc24b12","messageTitle":"add the ability to store whatever text entered by the user and display them back to the user when requested","messageBody":"","tags":["Level-2"],"fileTypesAndContributionMap":{"java":{"insertions":11,"deletions":1}}}]},{"date":"2021-01-28","commitResults":[{"hash":"566d76b99e03df64e9cc13adf5ff0edd61e3f281","messageTitle":"draft for level-3","messageBody":"","fileTypesAndContributionMap":{"java":{"insertions":37,"deletions":7}}},{"hash":"6bb2cc40559e67a52de01e45af3bd7bf96b02f70","messageTitle":"create Task class and add Mark as Done to Duke","messageBody":"","tags":["Level-3","A-CodingStandard"],"fileTypesAndContributionMap":{"java":{"insertions":74,"deletions":34}}}]}]},"authorFileTypeContributionMap":{"lihaoyangML":{"java":91,"md":9,"fxml":0,"sh":0,"bat":0,"gradle":0,"txt":0}},"authorContributionVariance":{"lihaoyangML":1226.8765},"authorDisplayNameMap":{"lihaoyangML":"LI H..YANG"}}
