[{"path":"data/duke.txt","fileType":"txt","lines":[{"lineNumber":1,"author":{"gitId":"e00426142"},"content":"T |1 |ivp"},{"lineNumber":2,"author":{"gitId":"e00426142"},"content":"D |0 |CG2027 Finals  |03 Mar 2021"}],"authorContributionMap":{"e00426142":2}},{"path":"src/main/java/Deadline.java","fileType":"java","lines":[{"lineNumber":1,"author":{"gitId":"e00426142"},"content":"public class Deadline extends Task {"},{"lineNumber":2,"author":{"gitId":"e00426142"},"content":""},{"lineNumber":3,"author":{"gitId":"e00426142"},"content":"    protected String by;"},{"lineNumber":4,"author":{"gitId":"e00426142"},"content":""},{"lineNumber":5,"author":{"gitId":"e00426142"},"content":"    public Deadline(String description, String by) {"},{"lineNumber":6,"author":{"gitId":"e00426142"},"content":"        super(description);"},{"lineNumber":7,"author":{"gitId":"e00426142"},"content":"        this.by \u003d by;"},{"lineNumber":8,"author":{"gitId":"e00426142"},"content":"    }"},{"lineNumber":9,"author":{"gitId":"e00426142"},"content":""},{"lineNumber":10,"author":{"gitId":"e00426142"},"content":"    public void setBy(String by) {"},{"lineNumber":11,"author":{"gitId":"e00426142"},"content":"        this.by \u003d by;"},{"lineNumber":12,"author":{"gitId":"e00426142"},"content":"    }"},{"lineNumber":13,"author":{"gitId":"e00426142"},"content":""},{"lineNumber":14,"author":{"gitId":"e00426142"},"content":"    public String getBy() {"},{"lineNumber":15,"author":{"gitId":"e00426142"},"content":"        return by;"},{"lineNumber":16,"author":{"gitId":"e00426142"},"content":"    }"},{"lineNumber":17,"author":{"gitId":"e00426142"},"content":""},{"lineNumber":18,"author":{"gitId":"e00426142"},"content":"    public String getType(){"},{"lineNumber":19,"author":{"gitId":"e00426142"},"content":"        return \"D\";"},{"lineNumber":20,"author":{"gitId":"e00426142"},"content":"    }"},{"lineNumber":21,"author":{"gitId":"e00426142"},"content":""},{"lineNumber":22,"author":{"gitId":"e00426142"},"content":"    @Override"},{"lineNumber":23,"author":{"gitId":"e00426142"},"content":"    public String toString() {"},{"lineNumber":24,"author":{"gitId":"e00426142"},"content":"        return \"[\" + getType() + \"]\" + \"[\" + getStatusIcon() + \"] \" +"},{"lineNumber":25,"author":{"gitId":"e00426142"},"content":"                description + \" (by: \" + by + \")\";"},{"lineNumber":26,"author":{"gitId":"e00426142"},"content":"    }"},{"lineNumber":27,"author":{"gitId":"e00426142"},"content":"    public String toFileString() {"},{"lineNumber":28,"author":{"gitId":"e00426142"},"content":"        return getType() + \" |\" + getStatusNum() + \" |\" + description + \" |\" + by;}"},{"lineNumber":29,"author":{"gitId":"e00426142"},"content":"}"},{"lineNumber":30,"author":{"gitId":"e00426142"},"content":""},{"lineNumber":31,"author":{"gitId":"e00426142"},"content":""},{"lineNumber":32,"author":{"gitId":"e00426142"},"content":""},{"lineNumber":33,"author":{"gitId":"e00426142"},"content":""}],"authorContributionMap":{"e00426142":33}},{"path":"src/main/java/Duke.java","fileType":"java","lines":[{"lineNumber":1,"author":{"gitId":"e00426142"},"content":"import java.util.ArrayList;"},{"lineNumber":2,"author":{"gitId":"e00426142"},"content":"import java.util.Scanner;"},{"lineNumber":3,"author":{"gitId":"e00426142"},"content":"import java.io.*;"},{"lineNumber":4,"author":{"gitId":"e00426142"},"content":"import java.io.IOException;"},{"lineNumber":5,"author":{"gitId":"e00426142"},"content":""},{"lineNumber":6,"author":{"gitId":"-"},"content":"public class Duke {"},{"lineNumber":7,"author":{"gitId":"e00426142"},"content":"    private static final String line \u003d \"____________________________________________________________\\n\";"},{"lineNumber":8,"author":{"gitId":"e00426142"},"content":"    public static File filePath \u003d new File(\"data/duke.txt\");"},{"lineNumber":9,"author":{"gitId":"e00426142"},"content":"    public static ArrayList\u003cTask\u003e tasks \u003d new ArrayList\u003c\u003e();"},{"lineNumber":10,"author":{"gitId":"e00426142"},"content":"    public static int index \u003d 0;"},{"lineNumber":11,"author":{"gitId":"e00426142"},"content":""},{"lineNumber":12,"author":{"gitId":"e00426142"},"content":""},{"lineNumber":13,"author":{"gitId":"e00426142"},"content":"    private static void appendToFile(String textToAppend) throws IOException {"},{"lineNumber":14,"author":{"gitId":"e00426142"},"content":"        FileWriter fw \u003d new FileWriter(\"data/duke.txt\", true); // create a FileWriter in append mode"},{"lineNumber":15,"author":{"gitId":"e00426142"},"content":"        fw.write(textToAppend);"},{"lineNumber":16,"author":{"gitId":"e00426142"},"content":"        fw.close();"},{"lineNumber":17,"author":{"gitId":"e00426142"},"content":"    }"},{"lineNumber":18,"author":{"gitId":"e00426142"},"content":""},{"lineNumber":19,"author":{"gitId":"-"},"content":"    public static void main(String[] args) {"},{"lineNumber":20,"author":{"gitId":"-"},"content":"        String logo \u003d \" ____        _        \\n\""},{"lineNumber":21,"author":{"gitId":"-"},"content":"                + \"|  _ \\\\ _   _| | _____ \\n\""},{"lineNumber":22,"author":{"gitId":"-"},"content":"                + \"| | | | | | | |/ / _ \\\\\\n\""},{"lineNumber":23,"author":{"gitId":"-"},"content":"                + \"| |_| | |_| |   \u003c  __/\\n\""},{"lineNumber":24,"author":{"gitId":"-"},"content":"                + \"|____/ \\\\__,_|_|\\\\_\\\\___|\\n\";"},{"lineNumber":25,"author":{"gitId":"e00426142"},"content":""},{"lineNumber":26,"author":{"gitId":"e00426142"},"content":""},{"lineNumber":27,"author":{"gitId":"e00426142"},"content":"        try {"},{"lineNumber":28,"author":{"gitId":"e00426142"},"content":"            printFileContents(filePath);"},{"lineNumber":29,"author":{"gitId":"e00426142"},"content":"        } catch (FileNotFoundException e) {"},{"lineNumber":30,"author":{"gitId":"e00426142"},"content":"            System.out.println(\"no file found\");"},{"lineNumber":31,"author":{"gitId":"e00426142"},"content":"            File dataDirectory \u003d new File(\"data\");"},{"lineNumber":32,"author":{"gitId":"e00426142"},"content":"            dataDirectory.mkdir();"},{"lineNumber":33,"author":{"gitId":"e00426142"},"content":"            File dukeFile \u003d new File(\"data/duke.txt\");"},{"lineNumber":34,"author":{"gitId":"e00426142"},"content":"            //dukeFile.createNewFile();"},{"lineNumber":35,"author":{"gitId":"e00426142"},"content":""},{"lineNumber":36,"author":{"gitId":"e00426142"},"content":"        }"},{"lineNumber":37,"author":{"gitId":"e00426142"},"content":""},{"lineNumber":38,"author":{"gitId":"e00426142"},"content":""},{"lineNumber":39,"author":{"gitId":"e00426142"},"content":"        String greet \u003d \"____________________________________________________________\\n\" +"},{"lineNumber":40,"author":{"gitId":"e00426142"},"content":"                \" Hello! I\u0027m Duke\\n\" +"},{"lineNumber":41,"author":{"gitId":"e00426142"},"content":"                \"____________________________________________________________\";"},{"lineNumber":42,"author":{"gitId":"e00426142"},"content":"        String exit \u003d \"____________________________________________________________\\n\" +"},{"lineNumber":43,"author":{"gitId":"e00426142"},"content":"                \"Bye. Hope to see you again!\\n\" +"},{"lineNumber":44,"author":{"gitId":"e00426142"},"content":"                \"____________________________________________________________\\n\";"},{"lineNumber":45,"author":{"gitId":"e00426142"},"content":"        System.out.println(logo);"},{"lineNumber":46,"author":{"gitId":"e00426142"},"content":"        System.out.println(greet);"},{"lineNumber":47,"author":{"gitId":"e00426142"},"content":"        System.out.print(\" What can I do for you?\\n\");"},{"lineNumber":48,"author":{"gitId":"e00426142"},"content":"        System.out.print(line);"},{"lineNumber":49,"author":{"gitId":"e00426142"},"content":""},{"lineNumber":50,"author":{"gitId":"e00426142"},"content":"        String input;"},{"lineNumber":51,"author":{"gitId":"e00426142"},"content":"        Scanner userInput \u003d new Scanner(System.in);"},{"lineNumber":52,"author":{"gitId":"e00426142"},"content":"        input \u003d userInput.nextLine();"},{"lineNumber":53,"author":{"gitId":"e00426142"},"content":""},{"lineNumber":54,"author":{"gitId":"e00426142"},"content":"        while (!input.equals(\"bye\")) {"},{"lineNumber":55,"author":{"gitId":"e00426142"},"content":""},{"lineNumber":56,"author":{"gitId":"e00426142"},"content":"            if (input.contains(\"todo\")) {"},{"lineNumber":57,"author":{"gitId":"e00426142"},"content":"                int dividerPosition \u003d input.indexOf(\" \");"},{"lineNumber":58,"author":{"gitId":"e00426142"},"content":"                String t \u003d input.substring(dividerPosition + 1);"},{"lineNumber":59,"author":{"gitId":"e00426142"},"content":"                if(dividerPosition\u003d\u003d-1 || t.equals(\"\") || !input.contains(\" \")){"},{"lineNumber":60,"author":{"gitId":"e00426142"},"content":"                    System.out.print(line);"},{"lineNumber":61,"author":{"gitId":"e00426142"},"content":"                    System.out.print(\"I don\u0027t quite understand.\" +  \"\\n\" + \"Please enter the command again.\" + \"\\n\");"},{"lineNumber":62,"author":{"gitId":"e00426142"},"content":"                    System.out.print(line);"},{"lineNumber":63,"author":{"gitId":"e00426142"},"content":"                } else {"},{"lineNumber":64,"author":{"gitId":"e00426142"},"content":"                    tasks.add(new Todo(t));"},{"lineNumber":65,"author":{"gitId":"e00426142"},"content":"                    System.out.print(line + \"Got it. I\u0027ve added this task:\" + \"\\n\" + new Todo(t) + \"\\n\" + \"Now you have \" + tasks.size() + \" tasks in the list.\" + \"\\n\" + line );"},{"lineNumber":66,"author":{"gitId":"e00426142"},"content":"                }"},{"lineNumber":67,"author":{"gitId":"e00426142"},"content":""},{"lineNumber":68,"author":{"gitId":"e00426142"},"content":"            } else if (input.contains(\"deadline\")) {"},{"lineNumber":69,"author":{"gitId":"e00426142"},"content":"                int dividerPosition \u003d input.indexOf(\" \");"},{"lineNumber":70,"author":{"gitId":"e00426142"},"content":"                int dividerPosition_1 \u003d input.indexOf(\"/\");"},{"lineNumber":71,"author":{"gitId":"e00426142"},"content":"                String d \u003d input.substring(dividerPosition + 1, dividerPosition_1);"},{"lineNumber":72,"author":{"gitId":"e00426142"},"content":"                String by \u003d input.substring(dividerPosition_1 + 4);"},{"lineNumber":73,"author":{"gitId":"e00426142"},"content":"                if(dividerPosition\u003d\u003d-1 || d.equals(\"\") || !input.contains(\" \")){ "},{"lineNumber":74,"author":{"gitId":"e00426142"},"content":"                    System.out.print(line);"},{"lineNumber":75,"author":{"gitId":"e00426142"},"content":"                    System.out.print(\"I don\u0027t quite understand.\" +  \"\\n\" + \"Please enter the command again.\" + \"\\n\");"},{"lineNumber":76,"author":{"gitId":"e00426142"},"content":"                    System.out.print(line);"},{"lineNumber":77,"author":{"gitId":"e00426142"},"content":"                } else {"},{"lineNumber":78,"author":{"gitId":"e00426142"},"content":"                    tasks.add(new Deadline(d, by));"},{"lineNumber":79,"author":{"gitId":"e00426142"},"content":"                    System.out.print(line + \"Got it. I\u0027ve added this task:\" + \"\\n\" + new Deadline(d,by) + \"\\n\" + \"Now you have \" + tasks.size() + \" tasks in the list.\" + \"\\n\" + line);"},{"lineNumber":80,"author":{"gitId":"e00426142"},"content":"                }"},{"lineNumber":81,"author":{"gitId":"e00426142"},"content":""},{"lineNumber":82,"author":{"gitId":"e00426142"},"content":"            } else if (input.contains(\"event\")) {"},{"lineNumber":83,"author":{"gitId":"e00426142"},"content":"                int dividerPosition \u003d input.indexOf(\" \");"},{"lineNumber":84,"author":{"gitId":"e00426142"},"content":"                int dividerPosition_1 \u003d input.indexOf(\"/\");"},{"lineNumber":85,"author":{"gitId":"e00426142"},"content":"                String e \u003d input.substring(dividerPosition + 1, dividerPosition_1);"},{"lineNumber":86,"author":{"gitId":"e00426142"},"content":"                String at \u003d input.substring(dividerPosition_1 + 4);"},{"lineNumber":87,"author":{"gitId":"e00426142"},"content":"                if(dividerPosition\u003d\u003d-1 || e.equals(\"\") || !input.contains(\" \")){"},{"lineNumber":88,"author":{"gitId":"e00426142"},"content":"                    System.out.print(line);"},{"lineNumber":89,"author":{"gitId":"e00426142"},"content":"                    System.out.print(\"I don\u0027t quite understand.\" +  \"\\n\" + \"Please enter the command again.\" + \"\\n\");"},{"lineNumber":90,"author":{"gitId":"e00426142"},"content":"                    System.out.print(line);"},{"lineNumber":91,"author":{"gitId":"e00426142"},"content":"                } else {"},{"lineNumber":92,"author":{"gitId":"e00426142"},"content":"                    tasks.add(new Event(e, at));"},{"lineNumber":93,"author":{"gitId":"e00426142"},"content":"                    System.out.print(line + \"Got it. I\u0027ve added this task:\" + \"\\n\"  + new Event(e, at) + \"\\n\" + \"Now you have \" + tasks.size() + \" tasks in the list.\" + \"\\n\" + line);"},{"lineNumber":94,"author":{"gitId":"e00426142"},"content":"                }"},{"lineNumber":95,"author":{"gitId":"e00426142"},"content":""},{"lineNumber":96,"author":{"gitId":"e00426142"},"content":"            } else if (input.equals(\"list\")) {"},{"lineNumber":97,"author":{"gitId":"e00426142"},"content":"                if (tasks.size() \u003d\u003d 0) {"},{"lineNumber":98,"author":{"gitId":"e00426142"},"content":"                    System.out.print(line);"},{"lineNumber":99,"author":{"gitId":"e00426142"},"content":"                    System.out.print(\"You have zero task at the moment.\" + \"\\n\");"},{"lineNumber":100,"author":{"gitId":"e00426142"},"content":"                    System.out.print(line);"},{"lineNumber":101,"author":{"gitId":"e00426142"},"content":"                } else {"},{"lineNumber":102,"author":{"gitId":"e00426142"},"content":""},{"lineNumber":103,"author":{"gitId":"e00426142"},"content":"                    System.out.print(line);"},{"lineNumber":104,"author":{"gitId":"e00426142"},"content":"                    System.out.print(\"Here are the tasks in your list: \" + \"\\n\");"},{"lineNumber":105,"author":{"gitId":"e00426142"},"content":""},{"lineNumber":106,"author":{"gitId":"e00426142"},"content":"                    for (int i \u003d 0; i \u003c tasks.size(); i++) {"},{"lineNumber":107,"author":{"gitId":"e00426142"},"content":"                        System.out.print(i + 1 + \".\" + tasks.get(i)+ \"\\n\");"},{"lineNumber":108,"author":{"gitId":"e00426142"},"content":"                    }"},{"lineNumber":109,"author":{"gitId":"e00426142"},"content":"                    System.out.print(line);"},{"lineNumber":110,"author":{"gitId":"e00426142"},"content":"                }"},{"lineNumber":111,"author":{"gitId":"e00426142"},"content":""},{"lineNumber":112,"author":{"gitId":"e00426142"},"content":"            } else if (input.contains(\"done\")) {"},{"lineNumber":113,"author":{"gitId":"e00426142"},"content":""},{"lineNumber":114,"author":{"gitId":"e00426142"},"content":"                int dividerPosition \u003d input.indexOf(\" \");"},{"lineNumber":115,"author":{"gitId":"e00426142"},"content":"                String taskNo \u003d input.substring(dividerPosition + 1);"},{"lineNumber":116,"author":{"gitId":"e00426142"},"content":"                try{"},{"lineNumber":117,"author":{"gitId":"e00426142"},"content":"                    int taskIndex \u003d Integer.parseInt(taskNo) - 1;"},{"lineNumber":118,"author":{"gitId":"e00426142"},"content":"                    if (taskIndex \u003e\u003dtasks.size()) {"},{"lineNumber":119,"author":{"gitId":"e00426142"},"content":"                        System.out.print(line);"},{"lineNumber":120,"author":{"gitId":"e00426142"},"content":"                        System.out.print(\"You have no such task.\" + \"\\n\");"},{"lineNumber":121,"author":{"gitId":"e00426142"},"content":"                        System.out.print(line);"},{"lineNumber":122,"author":{"gitId":"e00426142"},"content":"                    }"},{"lineNumber":123,"author":{"gitId":"e00426142"},"content":"                    else {"},{"lineNumber":124,"author":{"gitId":"e00426142"},"content":"                        tasks.get(taskIndex).markAsDone();"},{"lineNumber":125,"author":{"gitId":"e00426142"},"content":"                        System.out.print(line);"},{"lineNumber":126,"author":{"gitId":"e00426142"},"content":"                        System.out.print(\"Nice! I\u0027ve marked this task as done:\" + \"\\n\" + tasks.get(taskIndex) + \"\\n\");"},{"lineNumber":127,"author":{"gitId":"e00426142"},"content":"                        System.out.print(line);"},{"lineNumber":128,"author":{"gitId":"e00426142"},"content":"                    }"},{"lineNumber":129,"author":{"gitId":"e00426142"},"content":"                } catch (NumberFormatException e) {"},{"lineNumber":130,"author":{"gitId":"e00426142"},"content":"                    System.out.print(line);"},{"lineNumber":131,"author":{"gitId":"e00426142"},"content":"                    System.out.print(\"I don\u0027t quite understand.\" +  \"\\n\" + \"Please enter a number after done command.\" + \"\\n\");"},{"lineNumber":132,"author":{"gitId":"e00426142"},"content":"                    System.out.print(line);"},{"lineNumber":133,"author":{"gitId":"e00426142"},"content":"                }"},{"lineNumber":134,"author":{"gitId":"e00426142"},"content":"            } else if (input.contains(\"delete\")){"},{"lineNumber":135,"author":{"gitId":"e00426142"},"content":"                int dividerPosition \u003d input.indexOf(\" \");"},{"lineNumber":136,"author":{"gitId":"e00426142"},"content":"                String taskNo \u003d input.substring(dividerPosition + 1);"},{"lineNumber":137,"author":{"gitId":"e00426142"},"content":"                try{"},{"lineNumber":138,"author":{"gitId":"e00426142"},"content":"                    int taskIndex \u003d Integer.parseInt(taskNo) - 1;"},{"lineNumber":139,"author":{"gitId":"e00426142"},"content":"                    if (taskIndex \u003e\u003dtasks.size()) {"},{"lineNumber":140,"author":{"gitId":"e00426142"},"content":"                        System.out.print(line);"},{"lineNumber":141,"author":{"gitId":"e00426142"},"content":"                        System.out.print(\"You have no such task.\" + \"\\n\");"},{"lineNumber":142,"author":{"gitId":"e00426142"},"content":"                        System.out.print(line);"},{"lineNumber":143,"author":{"gitId":"e00426142"},"content":"                    }"},{"lineNumber":144,"author":{"gitId":"e00426142"},"content":"                    else {"},{"lineNumber":145,"author":{"gitId":"e00426142"},"content":"                        System.out.print(line);"},{"lineNumber":146,"author":{"gitId":"e00426142"},"content":"                        System.out.print(\"Noted. I\u0027ve removed this task: \" + \"\\n\" + tasks.get(taskIndex) + \"\\n\");"},{"lineNumber":147,"author":{"gitId":"e00426142"},"content":"                        tasks.remove(taskIndex);"},{"lineNumber":148,"author":{"gitId":"e00426142"},"content":"                        System.out.print(\"Now you have \" + tasks.size()+ \" tasks in the list.\"+\"\\n\");"},{"lineNumber":149,"author":{"gitId":"e00426142"},"content":"                        System.out.print(line);"},{"lineNumber":150,"author":{"gitId":"e00426142"},"content":"                    }"},{"lineNumber":151,"author":{"gitId":"e00426142"},"content":"                } catch (NumberFormatException e) {"},{"lineNumber":152,"author":{"gitId":"e00426142"},"content":"                    System.out.print(line);"},{"lineNumber":153,"author":{"gitId":"e00426142"},"content":"                    System.out.print(\"I don\u0027t quite understand.\" +  \"\\n\" + \"Please enter a number after done command.\" + \"\\n\");"},{"lineNumber":154,"author":{"gitId":"e00426142"},"content":"                    System.out.print(line);"},{"lineNumber":155,"author":{"gitId":"e00426142"},"content":"                }"},{"lineNumber":156,"author":{"gitId":"e00426142"},"content":""},{"lineNumber":157,"author":{"gitId":"e00426142"},"content":"            } else {"},{"lineNumber":158,"author":{"gitId":"e00426142"},"content":"                System.out.print(line);"},{"lineNumber":159,"author":{"gitId":"e00426142"},"content":"                System.out.print(\"Sorry, I didnt get you.\" + \"\\n\" + \"Please enter the command again.\" + \"\\n\");"},{"lineNumber":160,"author":{"gitId":"e00426142"},"content":"                System.out.print(line);"},{"lineNumber":161,"author":{"gitId":"e00426142"},"content":"            }"},{"lineNumber":162,"author":{"gitId":"e00426142"},"content":"            input \u003d userInput.nextLine();"},{"lineNumber":163,"author":{"gitId":"e00426142"},"content":"        }"},{"lineNumber":164,"author":{"gitId":"e00426142"},"content":"        try {"},{"lineNumber":165,"author":{"gitId":"e00426142"},"content":"            PrintWriter writer \u003d new PrintWriter(\"data/duke.txt\");"},{"lineNumber":166,"author":{"gitId":"e00426142"},"content":"            writer.print(\"\");"},{"lineNumber":167,"author":{"gitId":"e00426142"},"content":"            writer.close();"},{"lineNumber":168,"author":{"gitId":"e00426142"},"content":"            for (Task i : tasks) {"},{"lineNumber":169,"author":{"gitId":"e00426142"},"content":"                appendToFile(i.toFileString()+\"\\n\");"},{"lineNumber":170,"author":{"gitId":"e00426142"},"content":"            }"},{"lineNumber":171,"author":{"gitId":"e00426142"},"content":"        } catch (FileNotFoundException e){"},{"lineNumber":172,"author":{"gitId":"e00426142"},"content":"            System.out.println(\"File not found\");"},{"lineNumber":173,"author":{"gitId":"e00426142"},"content":"        } catch (IOException e) {"},{"lineNumber":174,"author":{"gitId":"e00426142"},"content":"            System.out.println(\"Unable to write to file\");"},{"lineNumber":175,"author":{"gitId":"e00426142"},"content":"        }"},{"lineNumber":176,"author":{"gitId":"e00426142"},"content":"        System.out.println(exit);"},{"lineNumber":177,"author":{"gitId":"e00426142"},"content":"        "},{"lineNumber":178,"author":{"gitId":"-"},"content":"    }"},{"lineNumber":179,"author":{"gitId":"e00426142"},"content":""},{"lineNumber":180,"author":{"gitId":"e00426142"},"content":"    private static void printFileContents(File filePath) throws FileNotFoundException {"},{"lineNumber":181,"author":{"gitId":"e00426142"},"content":"        Scanner s \u003d new Scanner(filePath); // create a Scanner using the File as the source"},{"lineNumber":182,"author":{"gitId":"e00426142"},"content":"        while (s.hasNext()) {"},{"lineNumber":183,"author":{"gitId":"e00426142"},"content":"            String[] dataEntry \u003d s.nextLine().split(\"\\\\|\");"},{"lineNumber":184,"author":{"gitId":"e00426142"},"content":"            if (dataEntry[0].contains(\"T\")) {"},{"lineNumber":185,"author":{"gitId":"e00426142"},"content":"                tasks.add(new Todo(dataEntry[2]));"},{"lineNumber":186,"author":{"gitId":"e00426142"},"content":"            } else if (dataEntry[0].contains(\"D\")) {"},{"lineNumber":187,"author":{"gitId":"e00426142"},"content":"                tasks.add(new Deadline(dataEntry[2],dataEntry[3]));"},{"lineNumber":188,"author":{"gitId":"e00426142"},"content":"            } else if (dataEntry[0].contains(\"E\")) {"},{"lineNumber":189,"author":{"gitId":"e00426142"},"content":"                tasks.add(new Event(dataEntry[2], dataEntry[3]));"},{"lineNumber":190,"author":{"gitId":"e00426142"},"content":"            }"},{"lineNumber":191,"author":{"gitId":"e00426142"},"content":"            if (dataEntry[1].equals(\"1\")) {"},{"lineNumber":192,"author":{"gitId":"e00426142"},"content":"                tasks.get(index).markAsDone();"},{"lineNumber":193,"author":{"gitId":"e00426142"},"content":"            }"},{"lineNumber":194,"author":{"gitId":"e00426142"},"content":"            index++;"},{"lineNumber":195,"author":{"gitId":"e00426142"},"content":""},{"lineNumber":196,"author":{"gitId":"e00426142"},"content":"        }"},{"lineNumber":197,"author":{"gitId":"-"},"content":"    }"},{"lineNumber":198,"author":{"gitId":"e00426142"},"content":""},{"lineNumber":199,"author":{"gitId":"e00426142"},"content":""},{"lineNumber":200,"author":{"gitId":"-"},"content":"}"}],"authorContributionMap":{"e00426142":190,"-":10}},{"path":"src/main/java/Event.java","fileType":"java","lines":[{"lineNumber":1,"author":{"gitId":"e00426142"},"content":"public class Event extends Task {"},{"lineNumber":2,"author":{"gitId":"e00426142"},"content":""},{"lineNumber":3,"author":{"gitId":"e00426142"},"content":"    protected String at;"},{"lineNumber":4,"author":{"gitId":"e00426142"},"content":""},{"lineNumber":5,"author":{"gitId":"e00426142"},"content":"    public Event(String description, String at) {"},{"lineNumber":6,"author":{"gitId":"e00426142"},"content":"        super(description);"},{"lineNumber":7,"author":{"gitId":"e00426142"},"content":"        this.at \u003d at;"},{"lineNumber":8,"author":{"gitId":"e00426142"},"content":"    }"},{"lineNumber":9,"author":{"gitId":"e00426142"},"content":""},{"lineNumber":10,"author":{"gitId":"e00426142"},"content":"    public void setAt(String at) {"},{"lineNumber":11,"author":{"gitId":"e00426142"},"content":"        this.at \u003d at;"},{"lineNumber":12,"author":{"gitId":"e00426142"},"content":"    }"},{"lineNumber":13,"author":{"gitId":"e00426142"},"content":""},{"lineNumber":14,"author":{"gitId":"e00426142"},"content":"    public String getAt() {"},{"lineNumber":15,"author":{"gitId":"e00426142"},"content":"        return at;"},{"lineNumber":16,"author":{"gitId":"e00426142"},"content":"    }"},{"lineNumber":17,"author":{"gitId":"e00426142"},"content":""},{"lineNumber":18,"author":{"gitId":"e00426142"},"content":"    public String getType(){"},{"lineNumber":19,"author":{"gitId":"e00426142"},"content":"        return \"E\";"},{"lineNumber":20,"author":{"gitId":"e00426142"},"content":"    }"},{"lineNumber":21,"author":{"gitId":"e00426142"},"content":""},{"lineNumber":22,"author":{"gitId":"e00426142"},"content":"    @Override"},{"lineNumber":23,"author":{"gitId":"e00426142"},"content":"    public String toString() {"},{"lineNumber":24,"author":{"gitId":"e00426142"},"content":"        return \"[\" + getType() + \"]\" + \"[\" + getStatusIcon() + \"] \" +"},{"lineNumber":25,"author":{"gitId":"e00426142"},"content":"                description + \" (at: \" + at + \")\"; }"},{"lineNumber":26,"author":{"gitId":"e00426142"},"content":""},{"lineNumber":27,"author":{"gitId":"e00426142"},"content":"    public String toFileString() {"},{"lineNumber":28,"author":{"gitId":"e00426142"},"content":"        return getType() + \" |\" + getStatusNum() + \" |\" + description + \" |\" + at;}"},{"lineNumber":29,"author":{"gitId":"e00426142"},"content":""},{"lineNumber":30,"author":{"gitId":"e00426142"},"content":""},{"lineNumber":31,"author":{"gitId":"e00426142"},"content":"}"},{"lineNumber":32,"author":{"gitId":"e00426142"},"content":""},{"lineNumber":33,"author":{"gitId":"e00426142"},"content":""},{"lineNumber":34,"author":{"gitId":"e00426142"},"content":""}],"authorContributionMap":{"e00426142":34}},{"path":"src/main/java/Task.java","fileType":"java","lines":[{"lineNumber":1,"author":{"gitId":"e00426142"},"content":"public abstract class Task {"},{"lineNumber":2,"author":{"gitId":"e00426142"},"content":"    protected String description;"},{"lineNumber":3,"author":{"gitId":"e00426142"},"content":"    protected boolean isDone;"},{"lineNumber":4,"author":{"gitId":"e00426142"},"content":""},{"lineNumber":5,"author":{"gitId":"e00426142"},"content":""},{"lineNumber":6,"author":{"gitId":"e00426142"},"content":""},{"lineNumber":7,"author":{"gitId":"e00426142"},"content":"    public Task(String description) {"},{"lineNumber":8,"author":{"gitId":"e00426142"},"content":"        this.description \u003d description;"},{"lineNumber":9,"author":{"gitId":"e00426142"},"content":"        isDone \u003d false;"},{"lineNumber":10,"author":{"gitId":"e00426142"},"content":"    }"},{"lineNumber":11,"author":{"gitId":"e00426142"},"content":""},{"lineNumber":12,"author":{"gitId":"e00426142"},"content":"    public String getDescription(){"},{"lineNumber":13,"author":{"gitId":"e00426142"},"content":"        return description;"},{"lineNumber":14,"author":{"gitId":"e00426142"},"content":"    }"},{"lineNumber":15,"author":{"gitId":"e00426142"},"content":""},{"lineNumber":16,"author":{"gitId":"e00426142"},"content":"    public String getStatusIcon() {"},{"lineNumber":17,"author":{"gitId":"e00426142"},"content":"        return (isDone ? \"\\u2713\" : \"\\u2718\"); //return tick or X symbols"},{"lineNumber":18,"author":{"gitId":"e00426142"},"content":"    }"},{"lineNumber":19,"author":{"gitId":"e00426142"},"content":"    public void markAsDone(){"},{"lineNumber":20,"author":{"gitId":"e00426142"},"content":"        isDone \u003d true;"},{"lineNumber":21,"author":{"gitId":"e00426142"},"content":"    }"},{"lineNumber":22,"author":{"gitId":"e00426142"},"content":"    public abstract String getType();"},{"lineNumber":23,"author":{"gitId":"e00426142"},"content":"    public String getStatusNum() { return (isDone ? \"1\" : \"0\");}"},{"lineNumber":24,"author":{"gitId":"e00426142"},"content":""},{"lineNumber":25,"author":{"gitId":"e00426142"},"content":""},{"lineNumber":26,"author":{"gitId":"e00426142"},"content":"    public String toString(){"},{"lineNumber":27,"author":{"gitId":"e00426142"},"content":"        return \"description: \" + description;"},{"lineNumber":28,"author":{"gitId":"e00426142"},"content":"    }"},{"lineNumber":29,"author":{"gitId":"e00426142"},"content":"    public String toFileString(){"},{"lineNumber":30,"author":{"gitId":"e00426142"},"content":"        return null;"},{"lineNumber":31,"author":{"gitId":"e00426142"},"content":"    };"},{"lineNumber":32,"author":{"gitId":"e00426142"},"content":""},{"lineNumber":33,"author":{"gitId":"e00426142"},"content":"}"}],"authorContributionMap":{"e00426142":33}},{"path":"src/main/java/Todo.java","fileType":"java","lines":[{"lineNumber":1,"author":{"gitId":"e00426142"},"content":"public class Todo extends Task {"},{"lineNumber":2,"author":{"gitId":"e00426142"},"content":"    protected boolean isDone;"},{"lineNumber":3,"author":{"gitId":"e00426142"},"content":""},{"lineNumber":4,"author":{"gitId":"e00426142"},"content":"    public Todo(String description) {"},{"lineNumber":5,"author":{"gitId":"e00426142"},"content":"        super(description);"},{"lineNumber":6,"author":{"gitId":"e00426142"},"content":"        isDone \u003d false;"},{"lineNumber":7,"author":{"gitId":"e00426142"},"content":"    }"},{"lineNumber":8,"author":{"gitId":"e00426142"},"content":""},{"lineNumber":9,"author":{"gitId":"e00426142"},"content":"    public void setDone(boolean done) {"},{"lineNumber":10,"author":{"gitId":"e00426142"},"content":"        isDone \u003d done;"},{"lineNumber":11,"author":{"gitId":"e00426142"},"content":"    }"},{"lineNumber":12,"author":{"gitId":"e00426142"},"content":""},{"lineNumber":13,"author":{"gitId":"e00426142"},"content":"    public boolean isDone() {"},{"lineNumber":14,"author":{"gitId":"e00426142"},"content":"        return isDone;"},{"lineNumber":15,"author":{"gitId":"e00426142"},"content":"    }"},{"lineNumber":16,"author":{"gitId":"e00426142"},"content":""},{"lineNumber":17,"author":{"gitId":"e00426142"},"content":"    public String getType(){"},{"lineNumber":18,"author":{"gitId":"e00426142"},"content":"        return \"T\";"},{"lineNumber":19,"author":{"gitId":"e00426142"},"content":"    }"},{"lineNumber":20,"author":{"gitId":"e00426142"},"content":"    @Override"},{"lineNumber":21,"author":{"gitId":"e00426142"},"content":"    public String toString() {"},{"lineNumber":22,"author":{"gitId":"e00426142"},"content":"        return \"[\" + getType() + \"]\" + \"[\" + getStatusIcon() + \"] \" + description;"},{"lineNumber":23,"author":{"gitId":"e00426142"},"content":"    }"},{"lineNumber":24,"author":{"gitId":"e00426142"},"content":""},{"lineNumber":25,"author":{"gitId":"e00426142"},"content":"    @Override"},{"lineNumber":26,"author":{"gitId":"e00426142"},"content":"    public String toFileString() {"},{"lineNumber":27,"author":{"gitId":"e00426142"},"content":"        return getType() + \" |\" + getStatusNum() +\" |\" + description;"},{"lineNumber":28,"author":{"gitId":"e00426142"},"content":"    }"},{"lineNumber":29,"author":{"gitId":"e00426142"},"content":"}"}],"authorContributionMap":{"e00426142":29}},{"path":"text-ui-test/input.txt","fileType":"txt","lines":[{"lineNumber":1,"author":{"gitId":"e00426142"},"content":"todo eat"}],"authorContributionMap":{"e00426142":1}}]
